LICENSE
MANIFEST.in
README.rst
setup.py
docs/Makefile
nsfds2/__init__.py
nsfds2/fdtd.py
nsfds2/solver.py
nsfds2.egg-info/PKG-INFO
nsfds2.egg-info/SOURCES.txt
nsfds2.egg-info/dependency_links.txt
nsfds2.egg-info/entry_points.txt
nsfds2.egg-info/requires.txt
nsfds2.egg-info/top_level.txt
nsfds2/init/__init__.py
nsfds2/init/config.py
nsfds2/init/fields.py
nsfds2/lib/__init__.py
nsfds2/lib/efluxes.py
nsfds2/lib/scapture.py
nsfds2/lib/sfilter.py
nsfds2/lib/vfluxes.py
nsfds2/lib/vorticity.py
nsfds2/utils/__init__.py
nsfds2/utils/array.py
nsfds2/utils/check.py
nsfds2/utils/files.py
nsfds2/utils/graphics.py
nsfds2/utils/headers.py
nsfds2/utils/misc.py
nsfds2/utils/sounds.py
nsfds2/utils/timing.py