Metadata-Version: 2.1
Name: nsfds2
Version: 0.17.3
Summary: Finite difference solver for Navier-Stokes equations
Home-page: https://github.com/ipselium/nsfds2
Author: Cyril Desjouy
Author-email: cyril.desjouy@univ-lemans.fr
License: GPL
Classifier: Development Status :: 4 - Beta
Classifier: Programming Language :: Python :: 3
Classifier: Intended Audience :: Science/Research
Classifier: Topic :: Scientific/Engineering :: Physics
Classifier: Topic :: Software Development :: Libraries :: Python Modules
Classifier: License :: OSI Approved :: GNU General Public License v3 or later (GPLv3+)
License-File: LICENSE
